.editorconfig
.gitignore
.nojekyll
.travis.yml
AUTHORS.rst
CONTRIBUTING.rst
HISTORY.rst
LICENSE
MANIFEST.in
Makefile
README.rst
index.html
requirements.txt
setup.cfg
setup.py
tox.ini
docs/Makefile
docs/authors.rst
docs/conf.py
docs/contributing.rst
docs/history.rst
docs/index.rst
docs/installation.rst
docs/make.bat
docs/readme.rst
docs/usage.rst
docs/xess.ico
docs/xess.png
docs/_build/singlehtml/index.html
docs/_build/singlehtml/_static/ajax-loader.gif
docs/_build/singlehtml/_static/basic.css
docs/_build/singlehtml/_static/classic.css
docs/_build/singlehtml/_static/comment-bright.png
docs/_build/singlehtml/_static/comment-close.png
docs/_build/singlehtml/_static/comment.png
docs/_build/singlehtml/_static/default.css
docs/_build/singlehtml/_static/doctools.js
docs/_build/singlehtml/_static/down-pressed.png
docs/_build/singlehtml/_static/down.png
docs/_build/singlehtml/_static/file.png
docs/_build/singlehtml/_static/jquery-1.11.1.js
docs/_build/singlehtml/_static/jquery.js
docs/_build/singlehtml/_static/minus.png
docs/_build/singlehtml/_static/plus.png
docs/_build/singlehtml/_static/pygments.css
docs/_build/singlehtml/_static/searchtools.js
docs/_build/singlehtml/_static/sidebar.js
docs/_build/singlehtml/_static/underscore-1.3.1.js
docs/_build/singlehtml/_static/underscore.js
docs/_build/singlehtml/_static/up-pressed.png
docs/_build/singlehtml/_static/up.png
docs/_build/singlehtml/_static/websupport.js
litterbox/__init__.py
litterbox/__main__.py
litterbox/litterbox.py
litterbox/spi.py
litterbox.egg-info/PKG-INFO
litterbox.egg-info/SOURCES.txt
litterbox.egg-info/dependency_links.txt
litterbox.egg-info/entry_points.txt
litterbox.egg-info/not-zip-safe
litterbox.egg-info/requires.txt
litterbox.egg-info/top_level.txt
tests/__init__.py
tests/test_litterbox.py