Metadata-Version: 1.1
Name: litterbox
Version: 0.2.2
Summary: A set of tools to manage all the crap for the CAT Board.
Home-page: https://github.com/devbisme/litterbox
Author: Dave Vandenbout
Author-email: devb@xess.com
License: MIT
Keywords: litterbox
Platform: UNKNOWN
Classifier: Development Status :: 2 - Pre-Alpha
Classifier: Intended Audience :: Developers
Classifier: License :: OSI Approved :: MIT License
Classifier: Natural Language :: English
Classifier: Programming Language :: Python :: 2.7
Classifier: Programming Language :: Python :: 3.4
